serpent.py
serpent-1.40.dist-info/LICENSE
serpent-1.40.dist-info/METADATA
serpent-1.40.dist-info/WHEEL
serpent-1.40.dist-info/top_level.txt
serpent-1.40.dist-info/RECORD
