Metadata-Version: 1.2
Name: serpent
Version: 1.40
Summary: Serialization based on ast.literal_eval
Home-page: https://github.com/irmen/Serpent
Author: Irmen de Jong
Author-email: irmen@razorvine.net
License: MIT
Keywords: serialization
Platform: any
Classifier: Development Status :: 5 - Production/Stable
Classifier: Intended Audience :: Developers
Classifier: License :: OSI Approved :: MIT License
Classifier: Natural Language :: English
Classifier: Operating System :: OS Independent
Classifier: Programming Language :: Python
Classifier: Programming Language :: Python :: 3.6
Classifier: Programming Language :: Python :: 3.7
Classifier: Programming Language :: Python :: 3.8
Classifier: Programming Language :: Python :: 3.9
Classifier: Topic :: Software Development
Requires-Python: >=3.2
